sentry_openproject/__init__.py
sentry_openproject/client.py
sentry_openproject/exceptions.py
sentry_openproject/plugin.py
sentry_openproject/utils.py
sentry_openproject-0.2.2.dist-info/DESCRIPTION.rst
sentry_openproject-0.2.2.dist-info/METADATA
sentry_openproject-0.2.2.dist-info/RECORD
sentry_openproject-0.2.2.dist-info/WHEEL
sentry_openproject-0.2.2.dist-info/entry_points.txt
sentry_openproject-0.2.2.dist-info/metadata.json
sentry_openproject-0.2.2.dist-info/top_level.txt
