Metadata-Version: 2.0
Name: sentry-openproject
Version: 0.2.2
Summary: A Sentry extension which integrates with OpenProject.
Home-page: http://github.com/versada/sentry-openproject
Author: Naglis Jonaitis
Author-email: naglis@versada.eu
License: BSD
Platform: UNKNOWN
Classifier: Intended Audience :: Developers
Classifier: Intended Audience :: System Administrators
Classifier: License :: OSI Approved :: BSD License
Classifier: Operating System :: OS Independent
Classifier: Topic :: Software Development
Requires-Dist: sentry (>=8.9.0)
Provides-Extra: tests
Requires-Dist: exam; extra == 'tests'
Requires-Dist: flake8 (<2.1,>=2.0); extra == 'tests'
Requires-Dist: pytest-cov; extra == 'tests'
Requires-Dist: sentry (>=8.9.0); extra == 'tests'
